<?xml version="1.0"?>

<accesscontrol name="roles">
	<permissions root="role">
		<permission id="superuser">
			<alias id="comp"/>
			<alias id="dlg"/>
			<alias id="page"/>
		</permission>
		<permission id="data-admin">
			<alias id="dlg/feescheduledataentry/add" />
			<alias id="dlg/feescheduleentry/add" />
			<alias id="dlg/staff/add" />
			<alias id="dlg/nurse/add" />
			<alias id="dlg/physician/add" />
			<alias id="dlg/org-main/add" />
			<alias id="dlg/org-ipa/add" />
			<alias id="dlg/org-provider/add" />
			<alias id="dlg/org-insurance/add" />
			<alias id="dlg/org-dept/add" />
			<alias id="dlg/misc-procedure/add" />
			<alias id="dlg/misc-procedure-item/add" />
			<alias id="dlg/appttype/add" />
			<alias id="dlg/template/add" />
			<alias id="dlg/feescheduledataentry/remove" />
			<alias id="dlg/feescheduleentry/remove" />
			<alias id="dlg/staff/remove" />
			<alias id="dlg/nurse/remove" />
			<alias id="dlg/physician/remove" />
			<alias id="dlg/org-main/remove" />
			<alias id="dlg/org-ipa/remove" />
			<alias id="dlg/org-provider/remove" />
			<alias id="dlg/org-insurance/remove" />
			<alias id="dlg/org-dept/remove" />
			<alias id="dlg/misc-procedure/remove" />
			<alias id="dlg/misc-procedure-item/remove" />
			<alias id="dlg/appttype/remove" />
			<alias id="dlg/template/remove" />
			<alias id="dlg/feescheduledataentry/update" />
			<alias id="dlg/feescheduleentry/update" />
			<alias id="dlg/staff/update" />
			<alias id="dlg/nurse/update" />
			<alias id="dlg/physician/update" />
			<alias id="dlg/org-main/update" />
			<alias id="dlg/org-ipa/update" />
			<alias id="dlg/org-provider/update" />
			<alias id="dlg/org-insurance/update" />
			<alias id="dlg/org-dept/update" />
			<alias id="dlg/misc-procedure/update" />
			<alias id="dlg/misc-procedure-item/update" />
			<alias id="dlg/appttype/update" />
			<alias id="dlg/template/update" />
		</permission>
	</permissions>
</accesscontrol>